cryodrgn/__init__.py
cryodrgn/_version.py
cryodrgn/analysis.py
cryodrgn/beta_schedule.py
cryodrgn/command_line.py
cryodrgn/config.py
cryodrgn/ctf.py
cryodrgn/dataset.py
cryodrgn/fft.py
cryodrgn/healpy_grid.json
cryodrgn/lattice.py
cryodrgn/lie_tools.py
cryodrgn/losses.py
cryodrgn/make_healpy.py
cryodrgn/masking.py
cryodrgn/models.py
cryodrgn/mrcfile.py
cryodrgn/pose.py
cryodrgn/pose_search.py
cryodrgn/shift_grid.py
cryodrgn/shift_grid3.py
cryodrgn/so3_grid.py
cryodrgn/source.py
cryodrgn/starfile.py
cryodrgn/utils.py
cryodrgn/commands/README.md
cryodrgn/commands/__init__.py
cryodrgn/commands/abinit_het.py
cryodrgn/commands/abinit_homo.py
cryodrgn/commands/analyze.py
cryodrgn/commands/analyze_landscape.py
cryodrgn/commands/analyze_landscape_full.py
cryodrgn/commands/backproject_voxel.py
cryodrgn/commands/direct_traversal.py
cryodrgn/commands/downsample.py
cryodrgn/commands/eval_images.py
cryodrgn/commands/eval_vol.py
cryodrgn/commands/filter.py
cryodrgn/commands/graph_traversal.py
cryodrgn/commands/parse_ctf_csparc.py
cryodrgn/commands/parse_ctf_star.py
cryodrgn/commands/parse_pose_csparc.py
cryodrgn/commands/parse_pose_star.py
cryodrgn/commands/parse_star.py
cryodrgn/commands/pc_traversal.py
cryodrgn/commands/train_dec.py
cryodrgn/commands/train_nn.py
cryodrgn/commands/train_vae.py
cryodrgn/commands_utils/README.md
cryodrgn/commands_utils/__init__.py
cryodrgn/commands_utils/add_psize.py
cryodrgn/commands_utils/analyze_convergence.py
cryodrgn/commands_utils/clean.py
cryodrgn/commands_utils/concat_pkls.py
cryodrgn/commands_utils/filter_cs.py
cryodrgn/commands_utils/filter_mrcs.py
cryodrgn/commands_utils/filter_pkl.py
cryodrgn/commands_utils/filter_star.py
cryodrgn/commands_utils/flip_hand.py
cryodrgn/commands_utils/fsc.py
cryodrgn/commands_utils/gen_mask.py
cryodrgn/commands_utils/invert_contrast.py
cryodrgn/commands_utils/make_movies.py
cryodrgn/commands_utils/parse_relion.py
cryodrgn/commands_utils/phase_flip.py
cryodrgn/commands_utils/plot_classes.py
cryodrgn-3.5.3.dist-info/licenses/LICENSE.txt
cryodrgn-3.5.3.dist-info/METADATA
cryodrgn-3.5.3.dist-info/WHEEL
cryodrgn-3.5.3.dist-info/entry_points.txt
cryodrgn-3.5.3.dist-info/top_level.txt
cryodrgn-3.5.3.dist-info/RECORD
