Metadata-Version: 2.4
Name: cryodrgn
Version: 3.5.3
Summary: cryoDRGN heterogeneous reconstruction
Author-email: Ellen Zhong <zhonge@princeton.edu>
Project-URL: Homepage, https://github.com/zhonge/cryodrgn
Classifier: Programming Language :: Python :: 3
Classifier: License :: OSI Approved :: GNU General Public License v3 (GPLv3)
Classifier: Operating System :: POSIX :: Linux
Requires-Python: >=3.10
License-File: LICENSE.txt
Requires-Dist: torch<2.6.0
Requires-Dist: pandas<3.0.0
Requires-Dist: numpy<1.27
Requires-Dist: matplotlib
Requires-Dist: pyyaml
Requires-Dist: scipy>=1.3.1
Requires-Dist: scikit-learn
Requires-Dist: seaborn
Requires-Dist: cufflinks
Requires-Dist: jupyterlab
Requires-Dist: notebook<7
Requires-Dist: umap-learn
Requires-Dist: ipywidgets<8
Requires-Dist: healpy
Requires-Dist: plotly<6
Requires-Dist: igraph
Requires-Dist: starfile
Provides-Extra: dev
Requires-Dist: build; extra == "dev"
Requires-Dist: myst-parser; extra == "dev"
Requires-Dist: pre-commit; extra == "dev"
Requires-Dist: pyright==1.1.300; extra == "dev"
Requires-Dist: pytest>=6; extra == "dev"
Requires-Dist: sphinx; extra == "dev"
Requires-Dist: sphinx-rtd-theme; extra == "dev"
Requires-Dist: twine; extra == "dev"
Dynamic: license-file
